Metadata-Version: 2.1
Name: root-relative
Version: 0.28
Summary: Module that allow to launch python module without requirements to start from working dir
Home-page: UNKNOWN
Author: liubomyr.ivanitskyi
Author-email: 
License: MIT
Platform: UNKNOWN
License-File: LICENSE.md
